README.md
setup.py
py_redis_simple_queue/__init__.py
py_redis_simple_queue/queue.py
py_redis_simple_queue/worker.py
py_redis_simple_queue.egg-info/PKG-INFO
py_redis_simple_queue.egg-info/SOURCES.txt
py_redis_simple_queue.egg-info/dependency_links.txt
py_redis_simple_queue.egg-info/requires.txt
py_redis_simple_queue.egg-info/top_level.txt
py_redis_simple_queue/test/__init__.py
py_redis_simple_queue/test/test_worker.py