Metadata-Version: 2.1
Name: py-redis-simple-queue
Version: 0.0.3
Summary: A simple but useful redis queue/worker
Home-page: https://github.com/lucasrc/py_redis_simple_queue
Author: Lucas Coutinho
Author-email: lrclucas@gmail.com
License: UNKNOWN
Platform: UNKNOWN
Classifier: Programming Language :: Python :: 2.7
Classifier: License :: OSI Approved :: MIT License
Classifier: Operating System :: OS Independent
